{
  "rulesDirectory": [
    "node_modules/tslint-microsoft-contrib",
    "node_modules/tslint-eslint-rules/dist/rules"
  ],
  "rules": {
    "object-literal-shorthand": true,
    "adjacent-overload-signatures": true,
    // "object-literal-key-quotes": [true, "as-needed"],
    // "no-for-in-array": true,
    "no-unsafe-finally": true,
    "no-mergeable-namespace": true,
    "linebreak-style": [
      true,
      "LF"
    ],
    "new-parens": true,
    "no-invalid-this": true,
    "use-isnan": true,
    "align": [
      true,
      "statements",
      "parameters"
    ],
    "ban": [
      true
    ],
    "class-name": true,
    "comment-format": [
      false
    ],
    "curly": true,
    "eofline": true,
    "forin": true,
    "indent": [
      true,
      "spaces"
    ],
    "interface-name": [
      false,
      "never-prefix"
    ],
    "jsdoc-format": true,
    "label-position": true,
    // "label-undefined": true,
    "max-line-length": [
      true,
      200
    ],
    "member-access": false,
    // "member-ordering": [true, "public-before-private", "static-before-instance", "variables-before-functions"],
    "no-angle-bracket-type-assertion": false,
    "no-any": false,
    "no-arg": true,
    "no-bitwise": false,
    "no-conditional-assignment": false,
    "no-consecutive-blank-lines": false,
    "no-console": [
      false
    ],
    "no-construct": true,
    "no-constructor-vars": false,
    "no-debugger": true,
    // "no-duplicate-key": true,
    "no-duplicate-variable": true,
    "no-empty": false,
    "no-eval": true,
    "no-inferrable-types": true,
    "no-internal-module": true,
    "no-null-keyword": false,
    "no-require-imports": false,
    "no-shadowed-variable": true,
    "no-string-literal": true,
    "no-trailing-whitespace": true,
    "no-unused-expression": true,
    "no-unused-variable": true,
    "no-use-before-declare": true,
    // "no-var-keyword": true,
    "no-var-requires": false,
    "object-literal-sort-keys": false,
    "one-line": [
      "check-else"
    ],
    "quotemark": [
      true,
      "single",
      "avoid-escape"
    ],
    "radix": true,
    "semicolon": [
      false,
      "never"
    ],
    "switch-default": true,
    "trailing-comma": [
      false,
      {
        "multiline": "always",
        "singleline": "never"
      }
    ],
    "triple-equals": [
      true
    ],
    "typedef": [
      false,
      "parameter",
      "arrow-parameter",
      "property-declaration",
      "member-variable-declaration"
    ],
    "typedef-whitespace": [
      true,
      {
        "call-signature": "nospace",
        "index-signature": "nospace",
        "parameter": "nospace",
        "property-declaration": "nospace",
        "variable-declaration": "nospace"
      },
      {
        "call-signature": "space",
        "index-signature": "space",
        "parameter": "space",
        "property-declaration": "space",
        "variable-declaration": "space"
      }
    ],
    "use-strict": [
      false
    ],
    "variable-name": [
      true,
      "check-format",
      "ban-keywords"
    ],
    "whitespace": [
      true,
      "check-branch",
      "check-decl",
      "check-operator",
      "check-separator",
      "check-module",
      "check-type"
    ],
    "one-variable-per-declaration": false,
    // "no-single-line-block-comment": true,
    "no-unnecessary-field-initialization": true,
    "no-typeof-undefined": true,
    "chai-vague-errors": true,
    "export-name": false,
    "missing-optional-annotation": true,
    "no-banned-terms": true,
    "no-constant-condition": false,
    "no-control-regex": true,
    "no-cookies": true,
    "no-document-write": false,
    "no-document-domain": true,
    "no-disable-auto-sanitization": true,
    "no-duplicate-case": true,
    "no-duplicate-parameter-names": true,
    "no-empty-interfaces": true,
    "no-exec-script": true,
    "no-function-constructor-with-string-args": true,
    "no-function-expression": false,
    "no-increment-decrement": false,
    "no-invalid-regexp": true,
    "no-for-in": true,
    "no-missing-visibility-modifiers": false,
    "no-multiline-string": false,
    "no-multiple-var-decl": true,
    // "no-unnecessary-bind": true,
    "no-unnecessary-semicolons": true,
    "no-octal-literal": true,
    "no-regex-spaces": true,
    "no-reserved-keywords": false,
    "no-sparse-arrays": true,
    "no-string-based-set-immediate": true,
    "no-string-based-set-interval": true,
    "no-string-based-set-timeout": true,
    // "no-unused-imports": true,
    "no-with-statement": true,
    "prefer-array-literal": false,
    "promise-must-complete": true,
    "react-no-dangerous-html": true,
    "use-named-parameter": true,
    "valid-typeof": true
  }
}
